topsis/algo.py
topsis/init.py
topsis/main.py
topsis_tarun_102217133-1.0.1.dist-info/METADATA
topsis_tarun_102217133-1.0.1.dist-info/WHEEL
topsis_tarun_102217133-1.0.1.dist-info/entry_points.txt
topsis_tarun_102217133-1.0.1.dist-info/top_level.txt
topsis_tarun_102217133-1.0.1.dist-info/RECORD
