Metadata-Version: 2.2
Name: topsis-tarun-102217133
Version: 1.0.1
Summary: Multiple Criteria Decision Making
Home-page: https://github.com/tarunkv169/topsis
Author: Tarun kumar
Author-email: tkumar_be22@thapar.edu
License: MIT
Classifier: License :: OSI Approved :: MIT License
Classifier: Programming Language :: Python :: 3.6
Classifier: Programming Language :: Python :: 3.7
Classifier: Programming Language :: Python :: 3.8
Dynamic: author
Dynamic: author-email
Dynamic: classifier
Dynamic: description
Dynamic: description-content-type
Dynamic: home-page
Dynamic: license
Dynamic: summary
